metaflow/__init__.py
metaflow/cli.py
metaflow/cmd_with_io.py
metaflow/current.py
metaflow/debug.py
metaflow/decorators.py
metaflow/environment.py
metaflow/event_logger.py
metaflow/exception.py
metaflow/flowspec.py
metaflow/graph.py
metaflow/includefile.py
metaflow/lint.py
metaflow/main_cli.py
metaflow/metaflow_config.py
metaflow/metaflow_profile.py
metaflow/metaflow_version.py
metaflow/monitor.py
metaflow/multicore_utils.py
metaflow/package.py
metaflow/parameters.py
metaflow/procpoll.py
metaflow/pylint_wrapper.py
metaflow/runtime.py
metaflow/sidecar.py
metaflow/sidecar_messages.py
metaflow/sidecar_worker.py
metaflow/task.py
metaflow/util.py
metaflow/client/__init__.py
metaflow/client/core.py
metaflow/client/filecache.py
metaflow/datastore/__init__.py
metaflow/datastore/datastore.py
metaflow/datastore/datastore_set.py
metaflow/datastore/local.py
metaflow/datastore/s3.py
metaflow/datastore/util/__init__.py
metaflow/datastore/util/s3tail.py
metaflow/datastore/util/s3util.py
metaflow/datatools/__init__.py
metaflow/datatools/s3.py
metaflow/datatools/s3op.py
metaflow/metadata/__init__.py
metaflow/metadata/local.py
metaflow/metadata/metadata.py
metaflow/metadata/service.py
metaflow/plugins/__init__.py
metaflow/plugins/catch_decorator.py
metaflow/plugins/debug_logger.py
metaflow/plugins/debug_monitor.py
metaflow/plugins/environment_decorator.py
metaflow/plugins/package_cli.py
metaflow/plugins/retry_decorator.py
metaflow/plugins/timeout_decorator.py
metaflow/plugins/aws/__init__.py
metaflow/plugins/aws/batch/__init__.py
metaflow/plugins/aws/batch/batch.py
metaflow/plugins/aws/batch/batch_cli.py
metaflow/plugins/aws/batch/batch_client.py
metaflow/plugins/aws/batch/batch_decorator.py
metaflow/plugins/conda/__init__.py
metaflow/plugins/conda/batch_bootstrap.py
metaflow/plugins/conda/conda.py
metaflow/plugins/conda/conda_environment.py
metaflow/plugins/conda/conda_flow_decorator.py
metaflow/plugins/conda/conda_step_decorator.py
metaflow/tutorials/00-helloworld/README.md
6D657461666C6F77-0.0.17.dist-info/LICENSE
6D657461666C6F77-0.0.17.dist-info/METADATA
6D657461666C6F77-0.0.17.dist-info/WHEEL
6D657461666C6F77-0.0.17.dist-info/entry_points.txt
6D657461666C6F77-0.0.17.dist-info/top_level.txt
6D657461666C6F77-0.0.17.dist-info/RECORD
